odoo/addons/hotel_reservation/README.rst
odoo/addons/hotel_reservation/__init__.py
odoo/addons/hotel_reservation/__manifest__.py
odoo/addons/hotel_reservation/LICENSE/LICENSE
odoo/addons/hotel_reservation/data/hotel_reservation_data.xml
odoo/addons/hotel_reservation/data/hotel_reservation_sequence.xml
odoo/addons/hotel_reservation/data/hotel_scheduler.xml
odoo/addons/hotel_reservation/i18n/da.po
odoo/addons/hotel_reservation/i18n/es.po
odoo/addons/hotel_reservation/i18n/fr.po
odoo/addons/hotel_reservation/i18n/fr_BE.po
odoo/addons/hotel_reservation/i18n/fr_FR.po
odoo/addons/hotel_reservation/i18n/hotel_reservation.pot
odoo/addons/hotel_reservation/i18n/sv.po
odoo/addons/hotel_reservation/models/__init__.py
odoo/addons/hotel_reservation/models/hotel_folio.py
odoo/addons/hotel_reservation/models/hotel_reservation.py
odoo/addons/hotel_reservation/models/hotel_reservation_line.py
odoo/addons/hotel_reservation/models/hotel_room.py
odoo/addons/hotel_reservation/models/hotel_room_reservation_line.py
odoo/addons/hotel_reservation/models/quick_room_reservation.py
odoo/addons/hotel_reservation/models/room_reservation_summary.py
odoo/addons/hotel_reservation/readme/CONTRIBUTORS.rst
odoo/addons/hotel_reservation/readme/DESCRIPTION.rst
odoo/addons/hotel_reservation/report/__init__.py
odoo/addons/hotel_reservation/report/hotel_reservation_report.py
odoo/addons/hotel_reservation/report/hotel_reservation_report.xml
odoo/addons/hotel_reservation/security/ir.model.access.csv
odoo/addons/hotel_reservation/static/description/HotelReserv.png
odoo/addons/hotel_reservation/static/description/done.png
odoo/addons/hotel_reservation/static/description/folio.png
odoo/addons/hotel_reservation/static/description/icon.png
odoo/addons/hotel_reservation/static/description/index.html
odoo/addons/hotel_reservation/static/description/res5.png
odoo/addons/hotel_reservation/static/description/res6.png
odoo/addons/hotel_reservation/static/description/room.png
odoo11_addon_hotel_reservation-11.0.1.0.0.99.dev43.dist-info/METADATA
odoo11_addon_hotel_reservation-11.0.1.0.0.99.dev43.dist-info/WHEEL
odoo11_addon_hotel_reservation-11.0.1.0.0.99.dev43.dist-info/top_level.txt
odoo11_addon_hotel_reservation-11.0.1.0.0.99.dev43.dist-info/RECORD
